odoo/addons/mail_activity_filter_internal_user/README.rst
odoo/addons/mail_activity_filter_internal_user/__init__.py
odoo/addons/mail_activity_filter_internal_user/__manifest__.py
odoo/addons/mail_activity_filter_internal_user/i18n/es.po
odoo/addons/mail_activity_filter_internal_user/i18n/it.po
odoo/addons/mail_activity_filter_internal_user/i18n/mail_activity_filter_internal_user.pot
odoo/addons/mail_activity_filter_internal_user/models/__init__.py
odoo/addons/mail_activity_filter_internal_user/models/mail_activity.py
odoo/addons/mail_activity_filter_internal_user/readme/CONTRIBUTORS.rst
odoo/addons/mail_activity_filter_internal_user/readme/DESCRIPTION.rst
odoo/addons/mail_activity_filter_internal_user/readme/HISTORY.rst
odoo/addons/mail_activity_filter_internal_user/static/description/icon.png
odoo/addons/mail_activity_filter_internal_user/static/description/index.html
odoo/addons/mail_activity_filter_internal_user/views/mail_activity.xml
odoo_addon_mail_activity_filter_internal_user-16.0.1.0.0.6.dist-info/METADATA
odoo_addon_mail_activity_filter_internal_user-16.0.1.0.0.6.dist-info/WHEEL
odoo_addon_mail_activity_filter_internal_user-16.0.1.0.0.6.dist-info/top_level.txt
odoo_addon_mail_activity_filter_internal_user-16.0.1.0.0.6.dist-info/RECORD
